[{"_id":"Oceanic Yachts","make_motor_name":"Oceanic Yachts","make_motor_logo":"http://dummyimage.com/182x100.png/cc0000/ffffff"},
{"_id":"Seafarer Yachts","make_motor_name":"Seafarer Yachts","make_motor_logo":"http://dummyimage.com/237x100.png/dddddd/000000"},
{"_id":"AquaLux Yachts","make_motor_name":"AquaLux Yachts","make_motor_logo":"http://dummyimage.com/117x100.png/ff4444/ffffff"},
{"_id":"MarineMaster Yachts","make_motor_name":"MarineMaster Yachts","make_motor_logo":"http://dummyimage.com/134x100.png/dddddd/000000"},
{"_id":"Nautical Star Yachts","make_motor_name":"Nautical Star Yachts","make_motor_logo":"http://dummyimage.com/238x100.png/cc0000/ffffff"},
{"_id":"WaveRunner Yachts","make_motor_name":"WaveRunner Yachts","make_motor_logo":"http://dummyimage.com/150x100.png/dddddd/000000"},
{"_id":"SailAway Yachts","make_motor_name":"SailAway Yachts","make_motor_logo":"http://dummyimage.com/218x100.png/cc0000/ffffff"},
{"_id":"Harbor Breeze Yachts","make_motor_name":"Harbor Breeze Yachts","make_motor_logo":"http://dummyimage.com/244x100.png/ff4444/ffffff"},
{"_id":"Island Paradise Yachts","make_motor_name":"Island Paradise Yachts","make_motor_logo":"http://dummyimage.com/244x100.png/5fa2dd/ffffff"},
{"_id":"SeaSpray Yachts","make_motor_name":"SeaSpray Yachts","make_motor_logo":"http://dummyimage.com/143x100.png/cc0000/ffffff"}]